<?xml version="1.0" encoding="utf-8"?>
<lemma schuttenr="273" corpus="nl" name="Tor" givenname="Joost Frederik" beginjaar="1776" eindjaar="1778" functie="zaakgelastigde" category="Turkije" url="http://resources.huygens.knaw.nl/retroapp/service_schutte/service_schutte/schutte_2/html/schutte_nederlandsevertegenwoordigersinbuitenland_0312.html">
  <line type="loopbaan">273. Joost Frederik Tor, secretaris en kanselier sedert 1767, werd bij res.</line>
  <line type="loopbaan">20 juni 1776 benoemd tot zaakgelastigde, had zijn eerste audiëntie</line>
  <line type="loopbaan">als zodanig 5 okt. 1776 en bleef dit tot de komst van Van Haeften</line>
  <line type="loopbaan">29 aug. 1778, was daarna weer kanselier en secretaris tot zijn vertrek</line>
  <line type="loopbaan">naar Holland 16 april 1779; bij res. 9 maart 1781 werd hij gelast zich</line>
  <line type="loopbaan">naar Venetië te begeven om daar mededeling te doen, dat H.H.M.</line>
  <line type="loopbaan">zich de zaak van Chomel en Jordan, kooplieden te Amsterdam,</line>
  <line type="loopbaan">313</line>
  <line type="loopbaan">tegen Cavalli te Venetië tot teruggave van de hun ontroofde kapita-</line>
  <line type="loopbaan">len, hadden aangetrokken en die procedures voor hun rekening</line>
  <line type="loopbaan">overnamen; bij res. 31 juli 1781 ontving hij de titel van resident bij</line>
  <line type="loopbaan">de senaat van Venetië; zijn zending had geen succes en hij werd bij</line>
  <line type="loopbaan">res. 13 mei 1783 teruggeroepen onder goedkeuring van het door</line>
  <line type="loopbaan">hem verrichte830.</line>
  <line type="hoofd">1778-1784 ambassadeur</line>
  <line type="loopbaan">Reinier van Haeften, heer van Ophemert en Zennewijnen, nr. 94.</line>
  <line type="hoofd">1784-1785 zaakgelastigde</line>
  <line type="loopbaan">George Ferdinand Kroll, nr. 91.</line>
  <line type="hoofd">1785-1808 ambassadeur</line>
</lemma>
