<?xml version="1.0" encoding="utf-8"?>
<lemma schuttenr="281" corpus="nl" name="Vries" givenname="David" intraposition="de" beginjaar="1651" eindjaar="1662" functie="hoofdconsul" category="Marokko" url="http://resources.huygens.knaw.nl/retroapp/service_schutte/service_schutte/schutte_2/html/schutte_nederlandsevertegenwoordigersinbuitenland_0383.html">
  <line type="loopbaan">281. David de Vries werd bij res. 12 okt. 1650 benoemd tot consul over</line>
  <line type="loopbaan">Oud- en Nieuw-Salee en ontving die dag zijn commissie als zodanig;</line>
  <line type="loopbaan">wegens het protest van Dopper, zie boven, werd zijn benoeming</line>
  <line type="loopbaan">opgeschort, maar bij res. 27 april 1651 werd hij definitief aangesteld</line>
  <line type="loopbaan">tot hoofdconsul over Salee, Tetuaen, Fedale, Knaffe, Asamor,</line>
  <line type="loopbaan">Masagam, Saffia, Magador, St. Cruys, Arsiel, Capo de Geer enz.;</line>
  <line type="loopbaan">bij res. 23 juli 1651 werd bepaald, dat de ratificatie van het verdrag</line>
  <line type="loopbaan">van 9 febr. 1651 voor vrede en het uitwisselen der gevangenen, door</line>
  <line type="loopbaan">de commandeur Gideon de Wildt gesloten, aan hem ter uitwisseling</line>
  <line type="loopbaan">zou worden toegezonden, f Salee 5 maart 16621059.</line>
  <line type="loopbaan">Zijn dienaar was (1655 tot 1657) Jan Jacome Gelthof, van Ant-</line>
  <line type="loopbaan">werpen.</line>
</lemma>
