<?xml version="1.0" encoding="utf-8"?>
<lemma schuttenr="226" corpus="bl" name="Tulemar" intraposition="Van" beginjaar="1704" eindjaar="1704" functie="envoyé" category="Nassau-(Diez-)Oranje" url="http://resources.huygens.knaw.nl/retroapp/service_schutte/service_schutte/schutte_1/html/schutte_buitenlandsevertegenwoordigersinnederland_0226.html">
  <line type="loopbaan">226. Van Tulemar wordt in 1704 vermeld als envoyé van (Johan</line>
  <line type="loopbaan">Willem Friso) prins van Oranje en Nassau(-Diez), logeerde in</line>
  <line type="loopbaan">de Gouden Leeuw op de Hofstraat.</line>
  <line type="loopbaan">U. NASSAU-DILLENBURG</line>
  <line type="loopbaan">(1718)-1730 agent</line>
</lemma>
