<?xml version="1.0" encoding="utf-8"?>
<lemma schuttenr="681" corpus="bl" name="Normandie" givenname="Gabriel" intraposition="de" beginjaar="1738" eindjaar="1745" functie="chargé d'affaires, agent (1742) van Genève" category="Zwitserland" url="http://resources.huygens.knaw.nl/retroapp/service_schutte/service_schutte/schutte_1/html/schutte_buitenlandsevertegenwoordigersinnederland_0687.html">
  <line type="loopbaan">681. Gabriel de Normandie, geb. Genève 1689/1690, koopman te</line>
  <line type="loopbaan">Amsterdam (1715); poorter aldaar 14 aug. 1716; lidmaat</line>
  <line type="loopbaan">Waalse kerk 19 mei 1720; was van 13 okt. 1738 tot 19 april</line>
  <line type="hoofd">1740 zaakgelastigde van Genève; vanaf 1742 wordt hij ver-</line>
  <line type="loopbaan">meld als agent; woonde in 1715 op het Rokin, in 1718 op de</line>
  <line type="loopbaan">Oude Turfmarkt bij de Grimmenissesluis, in 1719 te Parijs,</line>
  <line type="loopbaan">in 1721 op de Oude Zijds Achterburgwal bij de Bloedstraat,</line>
  <line type="loopbaan">in 1722 tot 1727 op het Rokin over de Nieuwe Zijds kapel of</line>
  <line type="loopbaan">het Haagse Veer, sedert 1742 op de Leidsegracht tussen de</line>
  <line type="hoofd">1598 Getuigen: Jacques Basnage. predikant van de Waalse gemeente te Rotterdam,</line>
  <line type="loopbaan">en Susanna du Moulin, zijn vrouw.</line>
  <line type="hoofd">1599 Getuigen: Henri Basnage de Beauval en Dlle. Jurieu.</line>
  <line type="hoofd">1600 Getuigen: Son Exc. Ie baron Pierre de Salis, envoyé extraordinaire de la</line>
  <line type="loopbaan">république des Grisons, en Magdelaine Bauldry née Basnage.</line>
  <line type="paginahoofd">688                                                              ZWITSERLAND</line>
  <line type="loopbaan">Heren- en de Keizersgracht; had in 1742 een buitenplaats,</line>
  <line type="loopbaan">begr. Amsterdam (Walenk.) 8 jan 1745.</line>
  <line type="personalia">Zoon van Jaques de Normandie en Olimpe Vernet; trouwde Ie Amsterdam</line>
  <line type="personalia">(Walenk.) 22 mei 1715 Françoise Desmaretz, ged. aldaar (Walenk.) 23 okt.</line>
  <line type="personalia">1695, lidmate Walenkerk 7 febr. 1712, begr. Amsterdam (Walenk.) 3 maart</line>
  <line type="personalia">1718, dochter van François Desmaretz, genaturaliseerd 26 sept. 1709, en</line>
  <line type="personalia">Marguerite Guy; trouwde 2e Leipzig (ondertr. Amsterdam 3 dec. 1719 op</line>
  <line type="personalia">akte van Ballin &amp; Foucault, notarissen in het Châtelet te Parijs, dd. 24 nov.</line>
  <line type="hoofd">1719 en van Daniel Grosjean, notaris te Genève, dd. 18 nov. 1719; att.</line>
  <line type="loopbaan">verleend 24 dec.) Charlotte le Clerc, geb. Genève, woonde in 1719 te Leipzig;</line>
  <line type="loopbaan">vertrok naar Genève 2 aug. 1746.</line>
  <line type="loopbaan">Uit het eerste huwelijk:</line>
  <line type="loopbaan">1. Jaques de Normandie, geb. Amsterdam 22 mei, ged. aldaar (O. Walenk.)</line>
  <line type="loopbaan">31 mei 17161601.</line>
  <line type="loopbaan">Uit het tweede huwelijk:</line>
  <line type="loopbaan">2. kind, begr. Amsterdam (Walenk.) 7 jan. 1721.</line>
  <line type="loopbaan">3. kind, begr. Amsterdam (Walenk.) 26 juni 1722.</line>
  <line type="loopbaan">4. Daniel de Normandie, geb. Amsterdam 25 febr., ged. aldaar (Walenk.) 7</line>
  <line type="loopbaan">maart 17231602, begr. aldaar (Walenk.) 2 juni 1746.</line>
  <line type="loopbaan">5. Michel de Normandie, geb. Amsterdam 12 juni, ged. aldaar (Walenk.) 18</line>
  <line type="loopbaan">juni 17241603.</line>
  <line type="loopbaan">6. Marie de Normandie, geb. Amsterdam 29 nov., ged. aldaar (Walenk.) 9</line>
  <line type="loopbaan">dec. 1725'604, vertrok naar Genève 2 aug. 1746.</line>
  <line type="loopbaan">7. kind, begr. Amsterdam (Walenk.) 25 juni 1727.</line>
  <line type="loopbaan">8. Jean Jacques de Normandie, geb. Amsterdam 19 mei, ged. aldaar (Wa-</line>
  <line type="loopbaan">lenk.) 30 mei 17281605.</line>
  <line type="loopbaan">9. Jacques de Normandie, geb. Amsterdam 13 aug., ged. aldaar (Walenk.) 17</line>
  <line type="loopbaan">aug. 17291606.</line>
  <line type="loopbaan">Hoge Raad van Adel, collectie Van der Lely van Oudewater, inv. nr. 860.</line>
  <line type="loopbaan">(1748) chargé d'affaires van Genève</line>
</lemma>
