<?xml version="1.0" encoding="utf-8"?>
<lemma schuttenr="205" corpus="bl" name="Bout" givenname="Adrianus" beginjaar="1706" eindjaar="1714" functie="agent" category="Keurvorstendom Palts" url="http://resources.huygens.knaw.nl/retroapp/service_schutte/service_schutte/schutte_1/html/schutte_buitenlandsevertegenwoordigersinnederland_0215.html">
  <line type="loopbaan">205. Adrianus Bout, ged. Leiden (P.k.) 9 maart 1661, solliciteur</line>
  <line type="loopbaan">militair te 's-Gravenhage (1696-1709); klerk ter secretarie</line>
  <line type="loopbaan">van de Raad van State (1695-1709); bediende in 1701 de vier</line>
  <line type="loopbaan">regimenten te paard en te voet van de keurvorst van de Palts;</line>
  <line type="loopbaan">wordt van 1706 tot 1714438 vermeld als agent van de keur-</line>
  <line type="loopbaan">vorst en in 1722 tot 1725 als agent van de keurvorst van</line>
  <line type="loopbaan">Trier; kocht omstreeks 1705 voor ƒ 7400 (hypotheek</line>
  <line type="loopbaan">ƒ 3000.10) het huis Nobelstraat 12, dat hij in 1716 weer ver-</line>
  <line type="loopbaan">kocht439, en op 30 nov. 1725 het buitengoed Hout-Rust in</line>
  <line type="loopbaan">Zegbroek440, f (imp. bet.) 's-Gravenhage 20 april 1733.</line>
  <line type="loopbaan">433 Getuigen: Andreas Eckhart, raadsheer van Zijne Hoogheid, en Susanna     Schel-</line>
  <line type="loopbaan">hammer.</line>
  <line type="loopbaan">434 Not. archief 's-Gravenhage, inv. nr. 653, 33, dd. 21 jan. 1676.</line>
  <line type="loopbaan">435 Id., inv. nr. 680, 377, dd. 6 aug. 1703.</line>
  <line type="loopbaan">436 Id., inv. nr. 682, 253, dd. 9 mei 1705</line>
  <line type="loopbaan">437 Id., inv. nr. 689, 239 sq., dd. 27 mei 1712.</line>
  <line type="loopbaan">438 Id., inv. nr. 691, 49, 75, 159 en 197.</line>
  <line type="loopbaan">439 Die Haghe 1964, 33.</line>
  <line type="paginahoofd">216                                                                DUITSE RIJK</line>
  <line type="personalia">Zoon van Egbert Bout, koopman te Leiden, en Maria Eysings; trouwde (on-</line>
  <line type="personalia">dertr. 's-Gravenhage 30 april 1690441 Anna Brackman, ged. 's-Gravenhage</line>
  <line type="personalia">(Gr.k.) 1 maart 1662, dochter van Bieter Brackman en Sophia van der Meu-</line>
  <line type="personalia">ïen.</line>
  <line type="personalia">Uit dit huwelijk:</line>
  <line type="personalia">1. Sophia Bout, ged. 's-Gravenhage (Kl.k.) 23 maart 1691442.</line>
  <line type="personalia">2. Mr. Bieter Bout, ged. 's-Gravenhage (N.k.) 3 juni 1693443, jur. student te</line>
  <line type="personalia">Leiden 17 jan. 1714, promoveerde aldaar 23 jan. 1714.</line>
  <line type="personalia">3. Mr. Johan Bout, ged. 's-Gravenhage (Kl.k.) 8 okt. 1694444, jur. student te</line>
  <line type="personalia">Leiden 17 jan. 1714, promoveerde aldaar 24 jan. 1714.</line>
  <line type="hoofd">1711-1716 extraordinaris envoyé</line>
</lemma>
