<?xml version="1.0" encoding="utf-8"?>
<lemma schuttenr="478" corpus="bl" name="Levsen" givenname="Christian" beginjaar="1797" eindjaar="1798" functie="chargé d'affaires" category="Denemarken en Noorwegen" url="http://resources.huygens.knaw.nl/retroapp/service_schutte/service_schutte/schutte_1/html/schutte_buitenlandsevertegenwoordigersinnederland_0463.html">
  <line type="loopbaan">478. Christian Levsen, volontair bij het eerste Sleeswijkse kantoor</line>
  <line type="loopbaan">van de rentekamer; werd 24 juni 1785 benoemd tot con-</line>
  <line type="loopbaan">sulaatssecretaris te Algiers, ontving 1 juli zijn aanstelling en</line>
  <line type="loopbaan">instructie als zodanig, legde de eed af 8 juli; 25 sept. 1789</line>
  <line type="loopbaan">benoemd tot legatiesecretaris te 's-Gravenhage, ontving 26</line>
  <line type="loopbaan">maart 1790 order om zich naar zijn nieuwe post te begeven,</line>
  <line type="loopbaan">fungeerde als chargé d'affaires van okt. 1790 tot mei 1792,</line>
  <line type="loopbaan">werd 16 juni 1797 benoemd tot chargé d'affaires, zond zijn</line>
  <line type="loopbaan">eerste bericht als zodanig 22 dec. 1797 en zijn laatste 15 juli</line>
  <line type="loopbaan">1798, had 29 juni toestemming tot verlof ontvangen, ver-</line>
  <line type="loopbaan">lengd 27 okt. 1798 en 8 maart 1799, werd 12 juni 1799 op zijn</line>
  <line type="loopbaan">verzoek ontslagen.</line>
  <line type="loopbaan">Legatiesecretaris was Mr. Willem Scholten van Oud-</line>
  <line type="loopbaan">Haarlem, nr. 479.</line>
  <line type="hoofd">1798 chargé d'affaires</line>
</lemma>
